panopticas/__init__.py
panopticas/cli.py
panopticas/constants.py
panopticas/core.py
panopticas-0.0.13.dist-info/licenses/LICENSE
panopticas-0.0.13.dist-info/METADATA
panopticas-0.0.13.dist-info/WHEEL
panopticas-0.0.13.dist-info/entry_points.txt
panopticas-0.0.13.dist-info/top_level.txt
panopticas-0.0.13.dist-info/RECORD
