Metadata-Version: 2.4
Name: panopticas
Version: 0.0.13
Summary: The panopticas file type and CLI tool.
Author-email: Peter Freiberg <peter.freiberg@gmail.com>
License-Expression: MIT
Project-URL: Homepage, https://panopticas.io
Project-URL: Issues, https://github.com/kospex/panopticas/issues
Project-URL: Repository, https://github.com/kospex/panopticas
Keywords: analytics,git
Classifier: Development Status :: 3 - Alpha
Classifier: Programming Language :: Python
Requires-Python: >=3.11
License-File: LICENSE
Requires-Dist: Click
Requires-Dist: prettytable
Requires-Dist: pathspec
Requires-Dist: twine
Requires-Dist: build
Dynamic: license-file
